ragtastic/__init__.py
ragtastic/resources/__init__.py
ragtastic/resources/batch_resource.py
ragtastic/resources/collection_resource.py
ragtastic/resources/document_resource.py
ragtastic/resources/query_resource.py
ragtastic/resources/resource.py
ragtastic/utils/__init__.py
ragtastic/utils/exceptions.py
ragtastic/utils/retry.py
ragtastic/utils/types.py
ragtastic-0.1.2.dist-info/METADATA
ragtastic-0.1.2.dist-info/WHEEL
ragtastic-0.1.2.dist-info/entry_points.txt
ragtastic-0.1.2.dist-info/RECORD
