Metadata-Version: 2.4
Name: ragtastic
Version: 0.1.2
Summary: Python bindings for the Ragtastic API
Author-email: Alexander Georgie <alex@useragtastic.com>
Requires-Python: >=3.8
Requires-Dist: pydantic>=2.11.4
Requires-Dist: requests>=2.32.3
